{
  "code": 0,
  "msg": "success!",
  "data": {
    "home_info": {
      "home_name": "Home",
      "home_img": "",
      "charging_power": "0.00",
      "power_unit": "W"
    },
    "solar_list": [],
    "pps_info": {
      "pps_list": [],
      "total_charging_power": "0.00",
      "power_unit": "W",
      "total_battery_power": "0.00",
      "updated_time": "",
      "pps_status": 0
    },
    "statistics": [
      {
        "type": "1",
        "total": "20.58",
        "unit": "kWh"
      },
      {
        "type": "2",
        "total": "20.52",
        "unit": "kg"
      },
      {
        "type": "3",
        "total": "6.59",
        "unit": "\u20ac"
      }
    ],
    "topology_type": "1",
    "solarbank_info": {
      "solarbank_list": [
        {
          "device_pn": "A17C1",
          "device_sn": "1CC2UKC60CE16V6T",
          "device_name": "Solarbank 2 E1600 Pro",
          "device_img": "https://public-aiot-fra-prod.s3.dualstack.eu-central-1.amazonaws.com/anker-power/public/product/2024/05/24/iot-admin/5iJoq1dk63i47HuR/picl_A17C1_normal%281%29.png",
          "battery_power": "99",
          "bind_site_status": "",
          "charging_power": "0",
          "power_unit": "W",
          "charging_status": "0",
          "status": "1",
          "wireless_type": "1",
          "main_version": "",
          "photovoltaic_power": "64",
          "output_power": "0",
          "create_time": 1735924816,
          "set_load_power": "",
          "sub_package_num": 0,
          "output_cutoff_data": 0,
          "is_display": true,
          "bat_charge_power": "64"
        },
        {
          "device_pn": "A17C0",
          "device_sn": "B91KD2ROPQVP6MLG",
          "device_name": "Solarbank Wohnzimmer",
          "device_img": "https://public-aiot-fra-prod.s3.dualstack.eu-central-1.amazonaws.com/anker-power/public/product/2024/05/10/iot-admin/FycLLqjHpYf0Bdab/20230719-144818.png",
          "battery_power": "64",
          "bind_site_status": "",
          "charging_power": "0",
          "power_unit": "W",
          "charging_status": "3",
          "status": "1",
          "wireless_type": "1",
          "main_version": "",
          "photovoltaic_power": "38",
          "output_power": "0",
          "create_time": 1735925245,
          "set_load_power": "",
          "sub_package_num": 0,
          "output_cutoff_data": 10,
          "is_display": true,
          "bat_charge_power": "37"
        },
        {
          "device_pn": "A17C0",
          "device_sn": "NEBY5IUHDXTGQKC2",
          "device_name": "Solarbank Wintergarten",
          "device_img": "https://public-aiot-fra-prod.s3.dualstack.eu-central-1.amazonaws.com/anker-power/public/product/2024/05/10/iot-admin/FycLLqjHpYf0Bdab/20230719-144818.png",
          "battery_power": "59",
          "bind_site_status": "",
          "charging_power": "0",
          "power_unit": "W",
          "charging_status": "3",
          "status": "1",
          "wireless_type": "1",
          "main_version": "",
          "photovoltaic_power": "38",
          "output_power": "0",
          "create_time": 1735925314,
          "set_load_power": "",
          "sub_package_num": 0,
          "output_cutoff_data": 10,
          "is_display": true,
          "bat_charge_power": "38"
        }
      ],
      "total_charging_power": "64",
      "power_unit": "W",
      "charging_status": "0",
      "total_battery_power": "0.99",
      "updated_time": "2025-01-21 09:50:21",
      "total_photovoltaic_power": "64",
      "total_output_power": "0.00",
      "display_set_power": false,
      "battery_discharge_power": "0",
      "ac_power": "0",
      "to_home_load": "0",
      "is_display_data": true,
      "solar_power_1": "0",
      "solar_power_2": "31",
      "solar_power_3": "33",
      "solar_power_4": "0",
      "other_input_power": "0",
      "micro_inverter_power": "33",
      "micro_inverter_power_limit": "0",
      "micro_inverter_low_power_limit": "0",
      "grid_to_battery_power": "0",
      "pei_heating_power": "0",
      "backup_info": {
        "start_time": 0,
        "end_time": 0,
        "full_time": 0
      }
    },
    "retain_load": "0W",
    "scene_mode": 3,
    "home_load_power": "212",
    "updated_time": "01-01-0001 00:00:00",
    "power_site_type": 5,
    "site_id": "f3edf80e-0c97-1eff-d675-ec87ec9b1b36",
    "powerpanel_list": [],
    "grid_info": {
      "grid_list": [
        {
          "device_pn": "SHEMP3",
          "device_sn": "7P5PFRUSCH7NK",
          "device_name": "Hauptstrom Keller",
          "device_img": "",
          "create_time": 1735925025,
          "status": "1",
          "bind_site_status": "",
          "wireless_type": ""
        }
      ],
      "photovoltaic_to_grid_power": "0",
      "grid_to_home_power": "212",
      "grid_status": 0,
      "has_history_data": true
    },
    "is_downgrade": false,
    "error_code": 0,
    "smart_plug_info": null,
    "feature_switch": {
      "0w_feed": true,
      "heating": false,
      "multi_pv": true,
      "shelly_meter": true,
      "smart_plug": true
    },
    "other_loads_power": "212",
    "priority_discharge_switch": 0,
    "display_priority_discharge_tips": 0,
    "priority_discharge_upgrade_devices": "",
    "style_id": 0,
    "is_show_priority_discharge": 0
  },
  "trace_id": "adfdb4a536861cce1e7adbadf6f21f2a"
}